PrintTolCalc/__init__.py
PrintTolCalc/cli.py
PrintTolCalc/tolerance.py
printtolcalc-0.3.2.2.dist-info/licenses/LICENSE.md
printtolcalc-0.3.2.2.dist-info/METADATA
printtolcalc-0.3.2.2.dist-info/WHEEL
printtolcalc-0.3.2.2.dist-info/entry_points.txt
printtolcalc-0.3.2.2.dist-info/top_level.txt
printtolcalc-0.3.2.2.dist-info/RECORD
