Metadata-Version: 2.4
Name: PrintTolCalc
Version: 0.3.2.2
Summary: PrintTolCalc - A simple CLI tool to calculate 3D print dimensional tolerance.
Author: NanashiTheNameless
Author-email: NanashiTheNameless <NanashiTheNameless@NamelessNanashi.dev>
Maintainer: NanashiTheNameless
Maintainer-email: NanashiTheNameless <NanashiTheNameless@NamelessNanashi.dev>
License: LicenseRef-OQL-1.2
Project-URL: Download, https://github.com/NanashiTheNameless/PrintTolCalc/releases/latest
Project-URL: Homepage, https://github.com/NanashiTheNameless/PrintTolCalc
Project-URL: GitHub-Sponsor, https://github.com/sponsors/NanashiTheNameless
Project-URL: BuyMeACoffee, https://buymeacoffee.com/NamelessNanashi
Classifier: Development Status :: 4 - Beta
Classifier: Natural Language :: English
Classifier: Programming Language :: Python
Classifier: Programming Language :: Python :: 3
Classifier: Programming Language :: Python :: 3.8
Classifier: Programming Language :: Python :: 3.9
Classifier: Programming Language :: Python :: 3.10
Classifier: Programming Language :: Python :: 3.11
Classifier: Programming Language :: Python :: 3.12
Classifier: Programming Language :: Python :: 3.13
Requires-Python: >=3.8
License-File: LICENSE.md
Dynamic: license-file
